{"id":591,"user_id":1445,"post_text":"\u0642\u0644\u0628\u0643 \u0628\u062d\u0627\u062c\u0629 \u0625\u0644\u0649 \u0647\u0630\u0647 \u0627\u0644\u0633\u0643\u064a\u0646\u0629\u060c \u0623\u0646\u0635\u062a\u2665\ufe0f. ","video_id":"kzWzZxf84Ic\/y","tags":"","keyword":"","comments_num":null,"views_num":0,"likes_num":0,"category_num":5,"status_like":1,"status_comment":0,"status":1,"added_date":"2022-08-27 21:05:51","last_update_date":null,"username":"arwa21","name":"\u0623\u0631\u0648\u0649 \u0645\u0635\u0637\u0641\u0649 \u0633\u0627\u0647\u0631","profile_image":null}