[{"path":"l\/80w1hwh40ow500z2yit0.jpg"},{"path":"l\/81igok13fkl7yuosuy20.jpg"},{"path":"l\/831ebubwxdxy3n42le2h.jpg"},{"path":"l\/85uekhh15454u2i5vqkx.jpg"},{"path":"l\/869j9dcfy2g966wctsft.jpg"},{"path":"l\/87qvhe0gpc2fk1s6o56d.jpg"},{"path":"l\/88hyukih03j4xfbs7kd5.jpg"},{"path":"l\/8ai2osuenh1ft5cw2czw.jpg"},{"path":"l\/8cs62o4427nyynhkdsis.jpg"},{"path":"l\/8er20q4g65uldbdafael.jpg"},{"path":"l\/8g6dwpy1odm1ueac11td.jpg"},{"path":"l\/8ikm16x5zbzjsmyzeb5i.jpg"},{"path":"l\/8jffkwz45pup4bxfd7ts.jpg"},{"path":"l\/8ju0m5ofz1m6ajfe4cgm.jpg"},{"path":"l\/8kxp3n7boq3xilbdd6fy.jpg"}]